torchbiggraph/VERSION.txt
torchbiggraph/__init__.py
torchbiggraph/batching.py
torchbiggraph/bucket_scheduling.py
torchbiggraph/checkpoint_manager.py
torchbiggraph/checkpoint_storage.py
torchbiggraph/config.py
torchbiggraph/distributed.py
torchbiggraph/edgelist.py
torchbiggraph/entitylist.py
torchbiggraph/eval.py
torchbiggraph/filtered_eval.py
torchbiggraph/graph_storages.py
torchbiggraph/losses.py
torchbiggraph/model.py
torchbiggraph/parameter_sharing.py
torchbiggraph/partitionserver.py
torchbiggraph/plugin.py
torchbiggraph/row_adagrad.py
torchbiggraph/rpc.py
torchbiggraph/schema.py
torchbiggraph/stats.py
torchbiggraph/tensorlist.py
torchbiggraph/train.py
torchbiggraph/types.py
torchbiggraph/util.py
torchbiggraph/converters/__init__.py
torchbiggraph/converters/dictionary.py
torchbiggraph/converters/export_to_tsv.py
torchbiggraph/converters/import_from_tsv.py
torchbiggraph/converters/utils.py
torchbiggraph/examples/__init__.py
torchbiggraph/examples/fb15k.py
torchbiggraph/examples/livejournal.py
torchbiggraph/examples/configs/fb15k_config.py
torchbiggraph/examples/configs/livejournal_config.py
torchbiggraph-1.0.0.dist-info/LICENSE.txt
torchbiggraph-1.0.0.dist-info/METADATA
torchbiggraph-1.0.0.dist-info/WHEEL
torchbiggraph-1.0.0.dist-info/entry_points.txt
torchbiggraph-1.0.0.dist-info/top_level.txt
torchbiggraph-1.0.0.dist-info/RECORD
