Metadata-Version: 2.1
Name: torchbiggraph
Version: 1.0.0
Summary: A distributed system to learn embeddings of large graphs
Home-page: https://github.com/facebookresearch/PyTorch-BigGraph
Author: Facebook AI Research
License: UNKNOWN
Project-URL: Source, https://github.com/facebookresearch/PyTorch-BigGraph
Project-URL: Bug Reports, https://github.com/facebookresearch/PyTorch-BigGraph/issues
Project-URL: Documentation, https://torchbiggraph.readthedocs.io/
Keywords: machine-learning,knowledge-base,graph-embedding,link-prediction
Platform: UNKNOWN
Classifier: Development Status :: 5 - Production/Stable
Classifier: Environment :: Console
Classifier: Intended Audience :: Science/Research
Classifier: License :: OSI Approved :: BSD License
Classifier: Operating System :: OS Independent
Classifier: Programming Language :: Python
Classifier: Programming Language :: Python :: 3
Classifier: Programming Language :: Python :: 3.6
Classifier: Programming Language :: Python :: 3.7
Classifier: Programming Language :: Python :: 3 :: Only
Classifier: Topic :: Scientific/Engineering :: Artificial Intelligence
Requires-Python: >=3.6, <4
Requires-Dist: attrs (>=18.2)
Requires-Dist: h5py (>=2.8)
Requires-Dist: numpy
Requires-Dist: setuptools
Requires-Dist: torch (>=1)
Requires-Dist: tqdm
Provides-Extra: docs
Requires-Dist: Sphinx ; extra == 'docs'
